requests_aws4auth/__init__.py
requests_aws4auth/aws4auth.py
requests_aws4auth/aws4signingkey.py
requests_aws4auth/exceptions.py
requests_aws4auth-1.3.0.dist-info/LICENSE
requests_aws4auth-1.3.0.dist-info/METADATA
requests_aws4auth-1.3.0.dist-info/WHEEL
requests_aws4auth-1.3.0.dist-info/top_level.txt
requests_aws4auth-1.3.0.dist-info/RECORD
