Metadata-Version: 2.1
Name: requests-aws4auth
Version: 1.3.0
Summary: AWS4 authentication for Requests
Home-page: https://github.com/tedder/requests-aws4auth
Download-URL: https://github.com/tedder/requests-aws4auth/tarball/1.3.0
Author: Ted Timmons
Author-email: ted@tedder.dev
License: MIT License
Keywords: requests authentication amazon web services aws s3 REST
Classifier: Development Status :: 5 - Production/Stable
Classifier: Intended Audience :: Developers
Classifier: Natural Language :: English
Classifier: License :: OSI Approved :: MIT License
Classifier: Programming Language :: Python
Classifier: Programming Language :: Python :: 3
Classifier: Programming Language :: Python :: 3.7
Classifier: Programming Language :: Python :: 3.8
Classifier: Programming Language :: Python :: 3.9
Classifier: Programming Language :: Python :: 3.10
Classifier: Programming Language :: Python :: 3.11
Classifier: Programming Language :: Python :: 3.12
Classifier: Topic :: Internet :: WWW/HTTP
Requires-Python: >=3.3
License-File: LICENSE
Requires-Dist: requests
Provides-Extra: httpx
Requires-Dist: httpx ; extra == 'httpx'
